Compiled from "Apple.java"
public class com.example.demo.domain.Apple implements java.io.Serializable {
  public java.lang.String getId();
    Code:
       0: aload_0
       1: getfield      #1                  // Field id:Ljava/lang/String;
       4: areturn

  public void setId(java.lang.String);
    Code:
       0: aload_0
       1: aload_1
       2: putfield      #1                  // Field id:Ljava/lang/String;
       5: return

  public java.lang.String getName();
    Code:
       0: aload_0
       1: getfield      #2                  // Field name:Ljava/lang/String;
       4: areturn

  public void setName(java.lang.String);
    Code:
       0: aload_0
       1: aload_1
       2: putfield      #2                  // Field name:Ljava/lang/String;
       5: return

  public java.math.BigDecimal getMoney();
    Code:
       0: aload_0
       1: getfield      #3                  // Field money:Ljava/math/BigDecimal;
       4: areturn

  public void setMoney(java.math.BigDecimal);
    Code:
       0: aload_0
       1: aload_1
       2: putfield      #3                  // Field money:Ljava/math/BigDecimal;
       5: return

  public com.example.demo.domain.Apple(java.lang.String, java.lang.String, java.math.BigDecimal);
    Code:
       0: aload_0
       1: invokespecial #4                  // Method java/lang/Object."<init>":()V
       4: aload_0
       5: aload_1
       6: putfield      #1                  // Field id:Ljava/lang/String;
       9: aload_0
      10: aload_2
      11: putfield      #2                  // Field name:Ljava/lang/String;
      14: aload_0
      15: aload_3
      16: putfield      #3                  // Field money:Ljava/math/BigDecimal;
      19: return

  public java.lang.String toString();
    Code:
       0: new           #5                  // class java/lang/StringBuilder
       3: dup
       4: invokespecial #6                  // Method java/lang/StringBuilder."<init>":()V
       7: ldc           #7                  // String Apple{id='
       9: invokevirtual #8                  // Method java/lang/StringBuilder.append:(Ljava/lang/String;)Ljava/lang/StringBuilder;
      12: aload_0
      13: getfield      #1                  // Field id:Ljava/lang/String;
      16: invokevirtual #8                  // Method java/lang/StringBuilder.append:(Ljava/lang/String;)Ljava/lang/StringBuilder;
      19: bipush        39
      21: invokevirtual #9                  // Method java/lang/StringBuilder.append:(C)Ljava/lang/StringBuilder;
      24: ldc           #10                 // String , name='
      26: invokevirtual #8                  // Method java/lang/StringBuilder.append:(Ljava/lang/String;)Ljava/lang/StringBuilder;
      29: aload_0
      30: getfield      #2                  // Field name:Ljava/lang/String;
      33: invokevirtual #8                  // Method java/lang/StringBuilder.append:(Ljava/lang/String;)Ljava/lang/StringBuilder;
      36: bipush        39
      38: invokevirtual #9                  // Method java/lang/StringBuilder.append:(C)Ljava/lang/StringBuilder;
      41: ldc           #11                 // String , money=
      43: invokevirtual #8                  // Method java/lang/StringBuilder.append:(Ljava/lang/String;)Ljava/lang/StringBuilder;
      46: aload_0
      47: getfield      #3                  // Field money:Ljava/math/BigDecimal;
      50: invokevirtual #12                 // Method java/lang/StringBuilder.append:(Ljava/lang/Object;)Ljava/lang/StringBuilder;
      53: bipush        125
      55: invokevirtual #9                  // Method java/lang/StringBuilder.append:(C)Ljava/lang/StringBuilder;
      58: invokevirtual #13                 // Method java/lang/StringBuilder.toString:()Ljava/lang/String;
      61: areturn
}
